hodgeys_kjv_db/__init__.py
hodgeys_kjv_db/exceptions.py
hodgeys_kjv_db/kjv.py
hodgeys_kjv_db/DATA/Bible.db
hodgeys_kjv_db-1.0.0.dist-info/METADATA
hodgeys_kjv_db-1.0.0.dist-info/WHEEL
hodgeys_kjv_db-1.0.0.dist-info/top_level.txt
hodgeys_kjv_db-1.0.0.dist-info/RECORD
