Metadata-Version: 2.1
Name: hodgeys-kjv-db
Version: 1.0.0
Summary: The King James Bible as a Python module
Home-page: https://github.com/HodgeyHodge/hodgeys_kjv_db
Author: Christopher Hodge
Author-email: christopher@hodgey.co.uk
License: MIT
Platform: UNKNOWN
Classifier: Intended Audience :: Developers
Classifier: License :: OSI Approved :: MIT License
Classifier: Programming Language :: Python
Classifier: Programming Language :: Python :: 3
Classifier: Programming Language :: Python :: 3.6
Classifier: Programming Language :: Python :: 3.7
Classifier: Programming Language :: Python :: 3.8
Classifier: Programming Language :: Python :: 3.9
Classifier: Operating System :: OS Independent
